voynich_decryption/__init__.py
voynich_decryption/__version__.py
voynich_decryption/api/__init__.py
voynich_decryption/api/app.py
voynich_decryption/api/routes.py
voynich_decryption/api/schemas.py
voynich_decryption/cli/__init__.py
voynich_decryption/core/__init__.py
voynich_decryption/core/morphemic_analyzer.py
voynich_decryption/core/statistical_validator.py
voynich_decryption/data/__init__.py
voynich_decryption/models/__init__.py
voynich_decryption/models/analysis_result.py
voynich_decryption/models/morpheme.py
voynich_decryption/models/word_analysis.py
voynich_decryption/pipelines/__init__.py
voynich_decryption/pipelines/analysis_pipeline.py
voynich_decryption/pipelines/reporting_pipeline.py
voynich_decryption/utils/__init__.py
voynich_decryption/visualization/__init__.py
voynich_morphemic_decryption-1.0.0.dist-info/METADATA
voynich_morphemic_decryption-1.0.0.dist-info/WHEEL
voynich_morphemic_decryption-1.0.0.dist-info/entry_points.txt
voynich_morphemic_decryption-1.0.0.dist-info/licenses/LICENSE
voynich_morphemic_decryption-1.0.0.dist-info/RECORD
