Metadata-Version: 2.4
Name: voynich-morphemic-decryption
Version: 1.0.0
Summary: Advanced morphemic analysis & decryption of Voynich Manuscript using statistical methods and NLP
License: MIT
License-File: LICENSE
Keywords: voynich,manuscript,morphemic-analysis,nlp,decryption
Author: Mateusz Piesiak
Author-email: mateuszpiesiak1990@gmail.com
Requires-Python: >=3.11,<4.0
Classifier: License :: OSI Approved :: MIT License
Classifier: Programming Language :: Python :: 3
Classifier: Programming Language :: Python :: 3.11
Classifier: Programming Language :: Python :: 3.12
Classifier: Programming Language :: Python :: 3.13
Classifier: Programming Language :: Python :: 3.14
Requires-Dist: fastapi (>=0.104.0,<0.105.0)
Requires-Dist: gensim (>=4.3.0,<5.0.0)
Requires-Dist: httpx (>=0.24.0,<0.25.0)
Requires-Dist: lightgbm (>=4.1.0,<5.0.0)
Requires-Dist: matplotlib (>=3.8.0,<4.0.0)
Requires-Dist: nltk (>=3.8.1,<4.0.0)
Requires-Dist: numpy (>=1.26.0,<2.0.0)
Requires-Dist: pandas (>=2.1.0,<3.0.0)
Requires-Dist: plotly (>=5.17.0,<6.0.0)
Requires-Dist: pydantic (>=2.4.0,<3.0.0)
Requires-Dist: pydantic-settings (>=2.0.0,<3.0.0)
Requires-Dist: python-dotenv (>=1.0.0,<2.0.0)
Requires-Dist: pyyaml (>=6.0.1,<7.0.0)
Requires-Dist: requests (>=2.31.0,<3.0.0)
Requires-Dist: rich (>=13.7.0,<14.0.0)
Requires-Dist: scikit-learn (>=1.3.0,<2.0.0)
Requires-Dist: scipy (>=1.11.0,<2.0.0)
Requires-Dist: seaborn (>=0.13.0,<0.14.0)
Requires-Dist: spacy (>=3.7.0,<4.0.0)
Requires-Dist: statsmodels (>=0.14.0,<0.15.0)
Requires-Dist: typer[all] (>=0.9.0,<0.10.0)
Requires-Dist: uvicorn[standard] (>=0.24.0,<0.25.0)
Requires-Dist: xgboost (>=2.0.0,<3.0.0)
Project-URL: Homepage, https://github.com/mati83moni/voynich-morphemic-decryption
Project-URL: Repository, https://github.com/mati83moni/voynich-morphemic-decryption
